cpgdata/__init__.py
cpgdata/cli/__init__.py
cpgdata/cli/index.py
cpgdata/cli/inventory.py
cpgdata/cli/main.py
cpgdata/cli/report.py
cpgdata/key_parser.lark
cpgdata/measurement.py
cpgdata/parser.py
cpgdata/pipe.py
cpgdata/rule.py
cpgdata/utils.py
cpgdata-0.6.0.dist-info/METADATA
cpgdata-0.6.0.dist-info/WHEEL
cpgdata-0.6.0.dist-info/entry_points.txt
cpgdata-0.6.0.dist-info/RECORD
