Metadata-Version: 2.1
Name: cpgdata
Version: 0.6.0
Summary: Cell painting gallery data handling and validation
Author: Ankur Kumar
Author-email: ank@leoank.me
Requires-Python: >=3.10,<4.0
Classifier: Programming Language :: Python :: 3
Classifier: Programming Language :: Python :: 3.10
Classifier: Programming Language :: Python :: 3.11
Classifier: Programming Language :: Python :: 3.12
Requires-Dist: click (>=8.1,<9.0)
Requires-Dist: cpgparser (>=0.2,<0.3)
Requires-Dist: joblib (>=1.3.2,<2.0.0)
Requires-Dist: lark (>=1.1.9,<2.0.0)
Requires-Dist: polars (>=1.9)
Requires-Dist: pyarrow (>=20.0,<21.0)
Requires-Dist: pydantic (>=2.4,<3.0)
Requires-Dist: tqdm (>=4.66,<5.0)
